s3torchconnector/__init__.py
s3torchconnector/example.py
s3torchconnector-0.0.1.dist-info/LICENSE
s3torchconnector-0.0.1.dist-info/METADATA
s3torchconnector-0.0.1.dist-info/WHEEL
s3torchconnector-0.0.1.dist-info/top_level.txt
s3torchconnector-0.0.1.dist-info/RECORD
